atomically/__init__.py
atomically/cli.py
atomically-0.2.0.dist-info/LICENSE
atomically-0.2.0.dist-info/METADATA
atomically-0.2.0.dist-info/WHEEL
atomically-0.2.0.dist-info/entry_points.txt
atomically-0.2.0.dist-info/top_level.txt
atomically-0.2.0.dist-info/RECORD
