Metadata-Version: 2.1
Name: atomically
Version: 0.2.0
Summary: Write the smallest possible OpenAPI and generate the rest
Author: Stephen Mizell
License: Apache-2.0
Project-URL: Homepage, https://github.com/smizell/atomically
Project-URL: Changelog, https://github.com/smizell/atomically/releases
Project-URL: Issues, https://github.com/smizell/atomically/issues
Project-URL: CI, https://github.com/smizell/atomically/actions
Classifier: License :: OSI Approved :: Apache Software License
Requires-Python: >=3.8
License-File: LICENSE
Requires-Dist: click
Requires-Dist: inflection
Requires-Dist: PyYAML
Provides-Extra: test
Requires-Dist: ipython ; extra == 'test'
Requires-Dist: pytest ; extra == 'test'
Requires-Dist: openapi-spec-validator ; extra == 'test'
Requires-Dist: snapshottest ; extra == 'test'
